sickle/__init__.py
sickle/_compat.py
sickle/app.py
sickle/iterator.py
sickle/models.py
sickle/oaiexceptions.py
sickle/response.py
sickle/utils.py
Sickle-0.7.0.dist-info/AUTHORS.rst
Sickle-0.7.0.dist-info/LICENSE
Sickle-0.7.0.dist-info/METADATA
Sickle-0.7.0.dist-info/WHEEL
Sickle-0.7.0.dist-info/top_level.txt
Sickle-0.7.0.dist-info/RECORD
