Metadata-Version: 1.1
Name: Sickle
Version: 0.7.0
Summary: A lightweight OAI client library for Python
Home-page: http://github.com/mloesch/sickle
Author: Mathias Loesch
Author-email: UNKNOWN
License: BSD
Keywords: oai oai-pmh
Platform: any
Classifier: Development Status :: 4 - Beta
Classifier: License :: OSI Approved :: BSD License
Classifier: Programming Language :: Python :: 2.6
Classifier: Programming Language :: Python :: 2.7
Classifier: Programming Language :: Python :: 3.3
Classifier: Programming Language :: Python :: 3.4
Classifier: Programming Language :: Python :: 3.5
Classifier: Topic :: Text Processing :: Markup :: XML
